archeanvision/__init__.py
archeanvision/api.py
archeanvision_api-1.0.3.dist-info/METADATA
archeanvision_api-1.0.3.dist-info/WHEEL
archeanvision_api-1.0.3.dist-info/top_level.txt
archeanvision_api-1.0.3.dist-info/RECORD
