Metadata-Version: 2.1
Name: archeanvision-api
Version: 1.0.3
Summary: Python wrapper for the updated Archean Vision API (using Bearer Token)
Home-page: https://github.com/Archean-Vision/archeanvision-api
Author: Charles Hajjar
Author-email: support@archeanvision.com
Classifier: Programming Language :: Python :: 3
Classifier: License :: OSI Approved :: MIT License
Classifier: Operating System :: OS Independent
Requires-Python: >=3.6
Requires-Dist: requests >=2.0.0
